osquery/TPipe.py
osquery/__init__.py
osquery/config_plugin.py
osquery/extension_client.py
osquery/extension_manager.py
osquery/logger_plugin.py
osquery/management.py
osquery/plugin.py
osquery/singleton.py
osquery/table_plugin.py
osquery/extensions/Extension.py
osquery/extensions/ExtensionManager.py
osquery/extensions/__init__.py
osquery/extensions/constants.py
osquery/extensions/ttypes.py
osquery-3.1.1.dist-info/LICENSE
osquery-3.1.1.dist-info/METADATA
osquery-3.1.1.dist-info/WHEEL
osquery-3.1.1.dist-info/top_level.txt
osquery-3.1.1.dist-info/RECORD
