Metadata-Version: 2.1
Name: osquery
Version: 3.1.1
Summary: Osquery Python API
Home-page: https://osquery.io
Author: osquery authors
Author-email: osquery@fb.com
License: BSD
Keywords: security databases operating systems
Classifier: Development Status :: 5 - Production/Stable
Classifier: Intended Audience :: System Administrators
Classifier: Topic :: Security
Classifier: License :: OSI Approved :: BSD License
Classifier: Programming Language :: Python :: 2
Classifier: Programming Language :: Python :: 2.7
Classifier: Programming Language :: Python :: 3
Classifier: Programming Language :: Python :: 3.3
Classifier: Programming Language :: Python :: 3.4
Classifier: Programming Language :: Python :: 3.6
License-File: LICENSE
Requires-Dist: thrift >=0.10
Requires-Dist: future
Requires-Dist: pywin32 ; sys_platform == "win32"
